LICENSE
MANIFEST.in
README.rst
setup.cfg
setup.py
django_ra.egg-info/PKG-INFO
django_ra.egg-info/SOURCES.txt
django_ra.egg-info/dependency_links.txt
django_ra.egg-info/entry_points.txt
django_ra.egg-info/requires.txt
django_ra.egg-info/top_level.txt
ra/__init__.py
ra/apps.py
ra/checks.py
ra/activity/__init__.py
ra/activity/admin.py
ra/activity/apps.py
ra/activity/models.py
ra/activity/migrations/0001_initial.py
ra/activity/migrations/__init__.py
ra/admin/__init__.py
ra/admin/admin.py
ra/admin/apps.py
ra/admin/base.py
ra/admin/forms.py
ra/admin/helpers.py
ra/admin/templates/adminlte/LICENSE
ra/admin/templates/adminlte/app_index.html
ra/admin/templates/adminlte/base.html
ra/admin/templates/adminlte/change_form.html
ra/admin/templates/adminlte/change_form_object_tools.html
ra/admin/templates/adminlte/change_list.html
ra/admin/templates/adminlte/change_list_object_tools.html
ra/admin/templates/adminlte/change_list_results.html
ra/admin/templates/adminlte/date_hierarchy.html
ra/admin/templates/adminlte/delete_confirmation.html
ra/admin/templates/adminlte/delete_selected_confirmation.html
ra/admin/templates/adminlte/filter.html
ra/admin/templates/adminlte/index.html
ra/admin/templates/adminlte/invalid_setup.html
ra/admin/templates/adminlte/logged_out.html
ra/admin/templates/adminlte/login.html
ra/admin/templates/adminlte/menu.html
ra/admin/templates/adminlte/object_history.html
ra/admin/templates/adminlte/pagination.html
ra/admin/templates/adminlte/popup_response.html
ra/admin/templates/adminlte/prepopulated_fields_js.html
ra/admin/templates/adminlte/print_base.html
ra/admin/templates/adminlte/report_list.html
ra/admin/templates/adminlte/report_list_form_buttons.html
ra/admin/templates/adminlte/report_list_forms.html
ra/admin/templates/adminlte/reports_menu.html
ra/admin/templates/adminlte/search_form.html
ra/admin/templates/adminlte/service-worker.js.html
ra/admin/templates/adminlte/submit_line.html
ra/admin/templates/adminlte/view.html
ra/admin/templates/adminlte/auth/user/add_form.html
ra/admin/templates/adminlte/auth/user/change_password.html
ra/admin/templates/adminlte/edit_inline/stacked.html
ra/admin/templates/adminlte/edit_inline/tabular.html
