Metadata-Version: 2.1
Name: django-ra
Version: 0.1.1
Summary: A light-weight effective Django based framework to create diverse business applications
Home-page: https://github.com/ra-systems/RA
Author: Ra Systems
Author-email: ramez@rasystems.io
License: UNKNOWN
Project-URL: Travis CI, https://travis-ci.org/ra-systems/RA/
Project-URL: Ra documentation, https://ra-framework.readthedocs.io/en/latest/
Project-URL: Ra source, https://github.com/ra-systems/RA
Platform: UNKNOWN
Classifier: Environment :: Web Environment
Classifier: Framework :: Django
Classifier: Framework :: Django :: 2.2
Classifier: Framework :: Django :: 3.0
Classifier: Intended Audience :: Developers
Classifier: Development Status :: 3 - Alpha
Classifier: License :: OSI Approved :: GNU Affero General Public License v3 or later (AGPLv3+)
Classifier: Natural Language :: English
Classifier: Operating System :: MacOS :: MacOS X
Classifier: Operating System :: POSIX
Classifier: Operating System :: POSIX :: BSD
Classifier: Operating System :: POSIX :: Linux
Classifier: Operating System :: Microsoft :: Windows
Classifier: Programming Language :: Python
Classifier: Programming Language :: Python :: 3
Classifier: Programming Language :: Python :: 3 :: Only
Classifier: Programming Language :: Python :: 3.6
Classifier: Programming Language :: Python :: 3.7
Classifier: Programming Language :: Python :: 3.8
Classifier: Topic :: Internet :: WWW/HTTP
Classifier: Topic :: Internet :: WWW/HTTP :: Dynamic Content
Requires-Python: >=3.6
